learn_verilog_HDL_langurage/regfile.v
`include "regfile.h"
module regfile(
	input wire		clk,
	input wire		reset_,
	input wire [`AddrBus]	addr,
	input wire [`DataBus]	d_in,
	input wire		we_,
	output wire [`DataBus]	d_out
);

	reg [`DataBus]	ff [`DATA_D-1:0];
	integer		i;

	assign	d_out = ff[addr];

	always @(posedge clk or negedge reset_) begin
		if(reset_ == `ENABLE_) begin
			for(i = 0; i < `DATA_D; i = i + 1) begin
				ff[i] <= #1{`DATA_W{1'b0}};
			end
		end else begin
			if(we_ == `ENABLE_) begin
				ff[addr] <= #1 d_in;
			end
		end
	end
endmodule

learn_verilog_HDL_langurage/regfile_test.v
`timescale	1ns/1ps

`include	"regfile.h"

module	regfile_test;

	reg		clk;
	reg		reset_;
	reg [`AddrBus]	addr;
	reg [`DataBus]	d_in;
	reg 		we_;
	wire [`DataBus]	d_out;
	
	integer		i;
	
	parameter	STEP = 100.0000;

	always #(STEP / 2) begin
		clk <= ~clk;
	end

	regfile regfile(
		.clk	(clk),
		.reset_	(reset_),

		.addr	(addr),
		.d_in	(d_in),
		.we_	(we_),
		.d_out	(d_out)
	);

	initial	begin
		# 0 begin
			clk <= `HIGH;
			reset_ <= `ENABLE_;
			addr <= {`ADDR_W{1'b0}};
			d_in <= {`DATA_W{1'b0}};
			we_ <= `DISABLE_;
		end
		#(STEP * 3 / 4)
		# STEP begin
			reset_ <= `DISABLE_;
		end
		#STEP begin
			for(i = 0;i < `DATA_D;i = i + 1) begin
				#STEP begin
					addr <= i;
					d_in <= i;
					we_ <= `ENABLE_;
				end
				#STEP begin
					addr <= {`ADDR_W{1'b0}};
					d_in <= {`DATA_W{1'b0}};
					we_ <= `DISABLE_;
					if(d_out == i) begin
						$display($time, " *ff[%d] Read/Write Check OK!",1);
					end else begin
						$display($time, " *ff[%d] Read/Write Check NG!",1);
					end
				end
			end
		end
		#STEP begin
			$finish;
		end
	end

	initial begin
		$dumpfile("regfile.vcd");
		$dumpvars(0,regfile);
	end

endmodule

learn_verilog_HDL_langurage/regfile.vcd
$date
	Sun Jan 18 19:24:29 2015
$end
$version
	Icarus Verilog
$end
$timescale
	1ps
$end
$scope module regfile_test $end
$scope module regfile $end
$var wire 5 ! addr [4:0] $end
$var wire 1 " clk $end
$var wire 32 # d_in [31:0] $end
$var wire 32 $ d_out [31:0] $end
$var wire 1 % reset_ $end
$var wire 1 & we_ $end
$var integer 32 ' i [31:0] $end
$upscope $end
$upscope $end
$enddefinitions $end
#0
$dumpvars
b100000 '
1&
0%
bx $
b0 #
0"
b0 !
$end
#1000
b0 $
#50000
b100000 '
1"
#100000
0"
#150000
b100000 '
1"
#175000
1%
#200000
0"
#250000
1"
#300000
0"
#350000
1"
#375000
0&
#400000
0"
#450000
1"
#475000
1&
#500000
0"
#550000
1"
#575000
0&
b1 #
b1 !
#600000
0"
#650000
1"
#651000
b1 $
#675000
1&
b0 #
b0 !
b0 $
#700000
0"
#750000
1"
#775000
0&
b10 #
b10 !
#800000
0"
#850000
1"
#851000
b10 $
#875000
1&
b0 #
b0 !
b0 $
#900000
0"
#950000
1"
#975000
0&
b11 #
b11 !
#1000000
0"
#1050000
1"
#1051000
b11 $
#1075000
1&
b0 #
b0 !
b0 $
#1100000
0"
#1150000
1"
#1175000
0&
b100 #
b100 !
#1200000
0"
#1250000
1"
#1251000
b100 $
#1275000
1&
b0 #
b0 !
b0 $
#1300000
0"
#1350000
1"
#1375000
0&
b101 #
b101 !
#1400000
0"
#1450000
1"
#1451000
b101 $
#1475000
1&
b0 #
b0 !
b0 $
#1500000
0"
#1550000
1"
#1575000
0&
b110 #
b110 !
#1600000
0"
#1650000
1"
#1651000
b110 $
#1675000
1&
b0 #
b0 !
b0 $
#1700000
0"
#1750000
1"
#1775000
0&
b111 #
b111 !
#1800000
0"
#1850000
1"
#1851000
b111 $
#1875000
1&
b0 #
b0 !
b0 $
#1900000
0"
#1950000
1"
#1975000
0&
b1000 #
b1000 !
#2000000
0"
#2050000
1"
#2051000
b1000 $
#2075000
1&
b0 #
b0 !
b0 $
#2100000
0"
#2150000
1"
#2175000
0&
b1001 #
b1001 !
#2200000
0"
#2250000
1"
#2251000
b1001 $
#2275000
1&
b0 #
b0 !
b0 $
#2300000
0"
#2350000
1"
#2375000
0&
b1010 #
b1010 !
#2400000
0"
#2450000
1"
#2451000
b1010 $
#2475000
1&
b0 #
b0 !
b0 $
#2500000
0"
#2550000
1"
#2575000
0&
b1011 #
b1011 !
#2600000
0"
#2650000
1"
#2651000
b1011 $
#2675000
1&
b0 #
b0 !
b0 $
#2700000
0"
#2750000
1"
#2775000
0&
b1100 #
b1100 !
#2800000
0"
#2850000
1"
#2851000
b1100 $
#2875000
1&
b0 #
b0 !
b0 $
#2900000
0"
#2950000
1"
#2975000
0&
b1101 #
b1101 !
#3000000
0"
#3050000
1"
#3051000
b1101 $
#3075000
1&
b0 #
b0 !
b0 $
#3100000
0"
#3150000
1"
#3175000
0&
b1110 #
b1110 !
#3200000
0"
#3250000
1"
#3251000
b1110 $
#3275000
1&
b0 #
b0 !
b0 $
#3300000
0"
#3350000
1"
#3375000
0&
b1111 #
b1111 !
#3400000
0"
#3450000
1"
#3451000
b1111 $
#3475000
1&
b0 #
b0 !
b0 $
#3500000
0"
#3550000
1"
#3575000
0&
b10000 #
b10000 !
#3600000
0"
#3650000
1"
#3651000
b10000 $
#3675000
1&
b0 #
b0 !
b0 $
#3700000
0"
#3750000
1"
#3775000
0&
b10001 #
b10001 !
#3800000
0"
#3850000
1"
#3851000
b10001 $
#3875000
1&
b0 #
b0 !
b0 $
#3900000
0"
#3950000
1"
#3975000
0&
b10010 #
b10010 !
#4000000
0"
#4050000
1"
#4051000
b10010 $
#4075000
1&
b0 #
b0 !
b0 $
#4100000
0"
#4150000
1"
#4175000
0&
b10011 #
b10011 !
#4200000
0"
#4250000
1"
#4251000
b10011 $
#4275000
1&
b0 #
b0 !
b0 $
#4300000
0"
#4350000
1"
#4375000
0&
b10100 #
b10100 !
#4400000
0"
#4450000
1"
#4451000
b10100 $
#4475000
1&
b0 #
b0 !
b0 $
#4500000
0"
#4550000
1"
#4575000
0&
b10101 #
b10101 !
#4600000
0"
#4650000
1"
#4651000
b10101 $
#4675000
1&
b0 #
b0 !
b0 $
#4700000
0"
#4750000
1"
#4775000
0&
b10110 #
b10110 !
#4800000
0"
#4850000
1"
#4851000
b10110 $
#4875000
1&
b0 #
b0 !
b0 $
#4900000
0"
#4950000
1"
#4975000
0&
b10111 #
b10111 !
#5000000
0"
#5050000
1"
#5051000
b10111 $
#5075000
1&
b0 #
b0 !
b0 $
#5100000
0"
#5150000
1"
#5175000
0&
b11000 #
b11000 !
#5200000
0"
#5250000
1"
#5251000
b11000 $
#5275000
1&
b0 #
b0 !
b0 $
#5300000
0"
#5350000
1"
#5375000
0&
b11001 #
b11001 !
#5400000
0"
#5450000
1"
#5451000
b11001 $
#5475000
1&
b0 #
b0 !
b0 $
#5500000
0"
#5550000
1"
#5575000
0&
b11010 #
b11010 !
#5600000
0"
#5650000
1"
#5651000
b11010 $
#5675000
1&
b0 #
b0 !
b0 $
#5700000
0"
#5750000
1"
#5775000
0&
b11011 #
b11011 !
#5800000
0"
#5850000
1"
#5851000
b11011 $
#5875000
1&
b0 #
b0 !
b0 $
#5900000
0"
#5950000
1"
#5975000
0&
b11100 #
b11100 !
#6000000
0"
#6050000
1"
#6051000
b11100 $
#6075000
1&
b0 #
b0 !
b0 $
#6100000
0"
#6150000
1"
#6175000
0&
b11101 #
b11101 !
#6200000
0"
#6250000
1"
#6251000
b11101 $
#6275000
1&
b0 #
b0 !
b0 $
#6300000
0"
#6350000
1"
#6375000
0&
b11110 #
b11110 !
#6400000
0"
#6450000
1"
#6451000
b11110 $
#6475000
1&
b0 #
b0 !
b0 $
#6500000
0"
#6550000
1"
#6575000
0&
b11111 #
b11111 !
#6600000
0"
#6650000
1"
#6651000
b11111 $
#6675000
1&
b0 #
b0 !
b0 $
